{
 "n": 12,
 "title": "SEGMENT 12 — George Streisinger and the transparent vertebrate",
 "duration": 281.81,
 "lines": [
  {
   "t": 0.05,
   "text": "SEGMENT 12 — George Streisinger and the transparent vertebrate"
  },
  {
   "t": 4.85,
   "text": "In 1981, a molecular biologist named George Streisinger at the University of Oregon published a short paper that, in retrospect, marks the founding of zebrafish biology."
  },
  {
   "t": 16.07,
   "text": "The paper was titled \"Production of clones of homozygous diploid zebra fish."
  },
  {
   "t": 22.6,
   "text": "\" It was technically modest."
  },
  {
   "t": 24.31,
   "text": "But it represented Streisinger's bet — a deliberate decision, in the spirit of Brenner's worm bet sixteen years earlier — that the zebrafish was the right vertebrate for genetics."
  },
  {
   "t": 35.06,
   "text": "Streisinger had spent his career in phage genetics — bacteriophages, the viruses that infect bacteria — and had been part of the heroic generation of molecular biologists who established the basic facts of gene structure and function."
  },
  {
   "t": 48.84,
   "text": "But by the late 1970s, he wanted to do something harder."
  },
  {
   "t": 52.65,
   "text": "He wanted to do vertebrate genetics."
  },
  {
   "t": 55.09,
   "text": "Not bacterial, not yeast, not invertebrate — vertebrate, with the same body plan as humans."
  },
  {
   "t": 61.75,
   "text": "And he wanted to do it at the scale and speed that the molecular geneticists were used to."
  },
  {
   "t": 66.62,
   "text": "The challenge was: vertebrates are not, in general, friendly to genetics."
  },
  {
   "t": 72.0,
   "text": "Mice take ten weeks per generation, produce a handful of pups per litter, and are expensive."
  },
  {
   "t": 78.05,
   "text": "Frogs are big and slow."
  },
  {
   "t": 79.69,
   "text": "Chicks are easy to embryo-manipulate but hard to breed for genetics."
  },
  {
   "t": 84.25,
   "text": "What Streisinger wanted was a vertebrate that bred like a fly — fast, in huge numbers, in tanks you could keep on a shelf."
  },
  {
   "t": 92.6,
   "text": "He picked the zebrafish, Danio rerio, a small striped tropical freshwater fish native to South Asia."
  },
  {
   "t": 99.74,
   "text": "Aquarium hobbyists had been keeping them for decades."
  },
  {
   "t": 102.81,
   "text": "Streisinger's lab adapted them for genetics, and the list of features he chose them for is striking."
  },
  {
   "t": 109.04,
   "text": "One: they breed fast and abundantly."
  },
  {
   "t": 112.29,
   "text": "A breeding pair lays about 200 eggs in a morning, every week."
  },
  {
   "t": 116.83,
   "text": "A small colony of a few hundred fish can produce tens of thousands of embryos per week."
  },
  {
   "t": 122.31,
   "text": "Two: they're cheap."
  },
  {
   "t": 123.84,
   "text": "Tanks of water, dry food, a temperature-controlled room."
  },
  {
   "t": 127.53,
   "text": "Compared to mice, zebrafish facilities cost a tenth as much per animal."
  },
  {
   "t": 133.16,
   "text": "Three: they generate fast."
  },
  {
   "t": 135.43,
   "text": "Generation time is about three months — slower than fly or worm, but fast for a vertebrate, far faster than mouse."
  },
  {
   "t": 144.09,
   "text": "Four — and this is the killer feature — the embryos are transparent."
  },
  {
   "t": 148.91,
   "text": "Zebrafish embryos are essentially clear blobs of cells, in a thin clear chorion, sitting in a dish of water."
  },
  {
   "t": 156.75,
   "text": "You can put one under a microscope and watch every cell divide, migrate, and differentiate, in real time, without dissecting anything."
  },
  {
   "t": 166.14,
   "text": "The vertebrate equivalent of the worm's transparency — and almost as informative."
  },
  {
   "t": 171.71,
   "text": "Five: external fertilization."
  },
  {
   "t": 174.39,
   "text": "Female fish lay eggs into water; males fertilize them externally."
  },
  {
   "t": 179.57,
   "text": "You can collect the fertilized eggs immediately, manipulate them, inject them with DNA or RNA, and watch development proceed."
  },
  {
   "t": 188.25,
   "text": "No surgery, no implantation, no womb."
  },
  {
   "t": 191.66,
   "text": "The embryo is on a microscope slide."
  },
  {
   "t": 194.14,
   "text": "Six: vertebrate body plan."
  },
  {
   "t": 196.26,
   "text": "Notochord, neural tube, somites, fins where our limbs would be, two-chambered heart that pumps blood through a circulatory system — all the standard vertebrate features."
  },
  {
   "t": 206.8,
   "text": "Most of what zebrafish do at the molecular level, mammals also do."
  },
  {
   "t": 211.25,
   "text": "The analogy: the zebrafish is the transparent vertebrate — Streisinger's idea: you want a vertebrate, you want lots of embryos, you want to SEE them develop; zebrafish gives you all three."
  },
  {
   "t": 223.68,
   "text": "The combination of fast breeding, external fertilization, and transparent embryos is unique."
  },
  {
   "t": 230.39,
   "text": "No other vertebrate has all three."
  },
  {
   "t": 232.66,
   "text": "And the body plan is conserved enough with humans that what you learn in fish often translates to clinically relevant biology."
  },
  {
   "t": 240.96,
   "text": "Streisinger died in 1984, only three years after his founding paper, but his lab and his students carried the project forward."
  },
  {
   "t": 249.71,
   "text": "By the mid-1990s, zebrafish was an established model organism, with stock centers, standardized protocols, and a growing community."
  },
  {
   "t": 258.77,
   "text": "The big idea: Streisinger's choice of zebrafish was the second great organism choice of late-twentieth-century biology, after Brenner's choice of the worm."
  },
  {
   "t": 268.35,
   "text": "Brenner gave us invertebrate genetics at single-cell resolution."
  },
  {
   "t": 272.9,
   "text": "Streisinger gave us vertebrate genetics at embryo-watching scale."
  },
  {
   "t": 277.45,
   "text": "Different niches, different organisms, both deliberately chosen."
  }
 ]
}