{
 "n": 4,
 "title": "Real World Applications",
 "duration": 70.85,
 "lines": [
  {
   "t": 0.05,
   "text": "Chapter 8, section 4. Real World Applications."
  },
  {
   "t": 4.47,
   "text": "Putting this all together at the table sounds daunting, but it gets faster the more you study."
  },
  {
   "t": 9.7,
   "text": "The strongest players don't think through each concept in isolation — the ideas merge into instinct."
  },
  {
   "t": 16.51,
   "text": "Before you bet, ask yourself whether your hand is better as a value bet, a bluff, or a check."
  },
  {
   "t": 22.99,
   "text": "Then ask which sizing puts your opponent in the hardest possible spot to respond correctly."
  },
  {
   "t": 28.41,
   "text": "Then ask whether the blockers in your hand point toward this bet or away from it."
  },
  {
   "t": 32.8,
   "text": "The goal at every decision point is the same: make your opponent's decision as uncomfortable as possible."
  },
  {
   "t": 39.51,
   "text": "A well-constructed range forces them to be wrong no matter what they do — call or fold."
  },
  {
   "t": 45.6,
   "text": "Against weak opposition you'll lean on exploitation, but against thinkers you need the full balanced approach."
  },
  {
   "t": 52.59,
   "text": "Start reviewing your own hands through this lens — what was the opponent's range, and what did my bet accomplish?"
  },
  {
   "t": 59.19,
   "text": "Over time you'll catch yourself choosing bluffs with better blockers without consciously running the math."
  },
  {
   "t": 65.16,
   "text": "That's the moment when game theory stops being a subject you study and starts being how you play."
  }
 ]
}